concierge_jinja/__init__.py
concierge_jinja/templater.py
concierge_jinja-0.2.0.dist-info/DESCRIPTION.rst
concierge_jinja-0.2.0.dist-info/METADATA
concierge_jinja-0.2.0.dist-info/RECORD
concierge_jinja-0.2.0.dist-info/WHEEL
concierge_jinja-0.2.0.dist-info/entry_points.txt
concierge_jinja-0.2.0.dist-info/metadata.json
concierge_jinja-0.2.0.dist-info/pbr.json
concierge_jinja-0.2.0.dist-info/top_level.txt
