Metadata-Version: 2.0
Name: concierge-jinja
Version: 0.2.0
Summary: Jinja2 templating for concierge
Home-page: https://github.com/9seconds/concierge-jinja
Author: Sergey Arkhipov
Author-email: serge@aerialsounds.org
License: MIT
Platform: UNKNOWN
Classifier: Intended Audience :: Information Technology
Classifier: Intended Audience :: System Administrators
Classifier: Operating System :: POSIX :: Linux
Classifier: Programming Language :: Python
Classifier: Programming Language :: Python :: 3
Classifier: Programming Language :: Python :: 3.4
Classifier: Programming Language :: Python :: 3.5
Requires-Dist: concierge (>=0.2,<1.0)
Requires-Dist: jinja2 (<3.0,>=2.0)
